socialite/__init__.py
socialite/actions.py
socialite/api.py
socialite/exceptions.py
socialite/helpers.py
socialite/commands/InstallCommand.py
socialite/commands/__init__.py
socialite/config/__init__.py
socialite/config/socialite.py
socialite/drivers/SocialiteBaseDriver.py
socialite/drivers/__init__.py
socialite/managers/SocialiteManager.py
socialite/managers/__init__.py
socialite/providers/SocialiteProvider.py
socialite/providers/__init__.py
socialite/strategy/MasoniteStrategy.py
socialite/strategy/__init__.py
masonite_socialite-0.0.5.dist-info/LICENSE
masonite_socialite-0.0.5.dist-info/METADATA
masonite_socialite-0.0.5.dist-info/WHEEL
masonite_socialite-0.0.5.dist-info/top_level.txt
masonite_socialite-0.0.5.dist-info/RECORD
